volt/__init__.py
volt/abc.py
volt/application.py
volt/channel.py
volt/client.py
volt/color.py
volt/components.py
volt/embed.py
volt/guild.py
volt/http.py
volt/interaction.py
volt/message.py
volt/user.py
volt/utils/__init__.py
volt/utils/abstracts.py
volt/utils/async_callback_handler.py
volt/utils/iterutils.py
volt/utils/log.py
volt/utils/loop_task.py
volt/utils/paginator.py
volt/utils/type_hint.py
volt.py-0.0.1.dist-info/METADATA
volt.py-0.0.1.dist-info/WHEEL
volt.py-0.0.1.dist-info/top_level.txt
volt.py-0.0.1.dist-info/RECORD
