Metadata-Version: 2.1
Name: volt.py
Version: 0.0.1
Summary: Wrapper of discord api for discord.py. Personal project for my study.
Home-page: https://github.com/Lapis0875/volt.py
Author: Lapis0875
Author-email: lapis0875@kakao.com
License: MIT
Keywords: discord api,discord.py,discord api wrapper
Platform: UNKNOWN
Classifier: Programming Language :: Python :: 3
Classifier: License :: OSI Approved :: MIT License
Classifier: Operating System :: OS Independent
Requires-Python: >=3.7
